shellinspector/__about__.py
shellinspector/__init__.py
shellinspector/__main__.py
shellinspector/logging.py
shellinspector/parser.py
shellinspector/reporter.py
shellinspector/runner.py
shellinspector-0.26.0.dist-info/METADATA
shellinspector-0.26.0.dist-info/WHEEL
shellinspector-0.26.0.dist-info/entry_points.txt
shellinspector-0.26.0.dist-info/RECORD
