Metadata-Version: 2.4
Name: shellinspector
Version: 0.26.0
Project-URL: Documentation, https://github.com/uberspace/shellinspector#readme
Project-URL: Issues, https://github.com/uberspace/shellinspector/issues
Project-URL: Source, https://github.com/uberspace/shellinspector
Author-email: "uberspace.de" <hallo@uberspace.de>
License: MIT License
Classifier: Development Status :: 4 - Beta
Classifier: Programming Language :: Python
Classifier: Programming Language :: Python :: 3.9
Classifier: Programming Language :: Python :: 3.10
Classifier: Programming Language :: Python :: 3.11
Classifier: Programming Language :: Python :: 3.12
Classifier: Programming Language :: Python :: Implementation :: CPython
Classifier: Programming Language :: Python :: Implementation :: PyPy
Requires-Python: >=3.9
Requires-Dist: pexpect==4.*
Requires-Dist: pyyaml>=6
Requires-Dist: termcolor==2.*
